<?xml version="1.0" ?>
<odoo>
    <data noupdate="0">
        <record id="payment_method_na" model="l10n_mx_edi.payment.method">
            <field name="code">NA</field>
            <field name="name">No Identificado</field>
        </record>
        <record id="payment_method_efectivo" model="l10n_mx_edi.payment.method">
            <field name="code">01</field>
            <field name="name">Efectivo</field>
        </record>
        <record id="payment_method_cheque" model="l10n_mx_edi.payment.method">
            <field name="code">02</field>
            <field name="name">Cheque nominativo</field>
        </record>
        <record id="payment_method_transferencia" model="l10n_mx_edi.payment.method">
            <field name="code">03</field>
            <field name="name">Transferencia electrónica de fondos</field>
        </record>
        <record id="payment_method_tarjeta_de_credito" model="l10n_mx_edi.payment.method">
            <field name="code">04</field>
            <field name="name">Tarjeta de Crédito</field>
        </record>
        <record id="payment_method_monedero_electronico" model="l10n_mx_edi.payment.method">
            <field name="code">05</field>
            <field name="name">Monedero Electrónico</field>
        </record>
        <record id="payment_method_dinero_electronico" model="l10n_mx_edi.payment.method">
            <field name="code">06</field>
            <field name="name">Dinero Electrónico</field>
        </record>
        <record id="payment_method_vales_despensa" model="l10n_mx_edi.payment.method">
            <field name="code">08</field>
            <field name="name">Vales de despensa</field>
        </record>
        <record id="payment_method_tarjeta_debito" model="l10n_mx_edi.payment.method">
            <field name="code">28</field>
            <field name="name">Tarjeta de Débito</field>
        </record>
        <record id="payment_method_tarjeta_servicio" model="l10n_mx_edi.payment.method">
            <field name="code">29</field>
            <field name="name">Tarjeta de Servicio</field>
        </record>
        <record id="payment_method_otros" model="l10n_mx_edi.payment.method">
            <field name="code">99</field>
            <field name="name">Otros</field>
        </record>
     </data>
</odoo>
